buzzshot/__init__.py
buzzshot/api/__init__.py
buzzshot/api/client.py
buzzshot/api/core/__init__.py
buzzshot/api/core/api_error.py
buzzshot/api/core/datetime_utils.py
buzzshot/api/core/jsonable_encoder.py
buzzshot/api/core/remove_none_from_headers.py
buzzshot/api/types/__init__.py
buzzshot/api/types/account.py
buzzshot/api/types/extra_fields_item.py
buzzshot/api/types/game.py
buzzshot/api/types/game_complete.py
buzzshot/api/types/games.py
buzzshot/api/types/games_response.py
buzzshot/api/types/group.py
buzzshot/api/types/groups_response.py
buzzshot/api/types/locations_response.py
buzzshot/api/types/photo.py
buzzshot/api/types/photos_item.py
buzzshot/api/types/photos_response.py
buzzshot/api/types/player.py
buzzshot/api/types/players_response.py
buzzshot/api/types/processed_photo_details.py
buzzshot/api/types/room.py
buzzshot/py.typed
buzzshotdev-0.0.2.dist-info/METADATA
buzzshotdev-0.0.2.dist-info/WHEEL
buzzshotdev-0.0.2.dist-info/RECORD
